dnadesign/__init__.py
dnadesign/cffi_bindings.py
dnadesign/clone.py
dnadesign/definitions.h
dnadesign/fragment.py
dnadesign/libdnadesign.dylib
dnadesign/libdnadesign.h
dnadesign/parsers.py
tests/__init__.py
tests/test_clone.py
tests/test_fasta_parser.py
tests/test_fastq_parser.py
tests/test_fragment.py
tests/test_genbank_parser.py
dnadesign-0.1.8.dist-info/METADATA
dnadesign-0.1.8.dist-info/WHEEL
dnadesign-0.1.8.dist-info/top_level.txt
dnadesign-0.1.8.dist-info/RECORD
